flipexception/__init__.py
flipexception/flipexception.py
FlipException-0.5.dist-info/LICENSE
FlipException-0.5.dist-info/METADATA
FlipException-0.5.dist-info/WHEEL
FlipException-0.5.dist-info/top_level.txt
FlipException-0.5.dist-info/RECORD
