Metadata-Version: 2.1
Name: FlipException
Version: 0.5
Summary: The best way to flip an exception out of rage
Home-page: https://github.com/xeBuz/FlipException
Author: Jesus Roldan
Author-email: jesus.roldan@gmail.com
License: Mozilla Public License
Platform: any
Classifier: Development Status :: 4 - Beta
Classifier: Environment :: Console
Classifier: Intended Audience :: Developers
Classifier: License :: OSI Approved :: Mozilla Public License 2.0 (MPL 2.0)
Classifier: Operating System :: Unix
Classifier: Operating System :: MacOS
Classifier: Operating System :: POSIX :: BSD
Classifier: Operating System :: POSIX :: Linux
Classifier: Programming Language :: Python
Classifier: Topic :: Software Development
Classifier: Topic :: Software Development :: Libraries
Classifier: Topic :: Software Development :: User Interfaces
Classifier: Topic :: Terminals
Requires-Dist: upsidedown (==0.4)
